arrowport/__init__.py
arrowport/__main__.py
arrowport/cli.py
arrowport/constants.py
arrowport/api/__init__.py
arrowport/api/app.py
arrowport/config/__init__.py
arrowport/config/settings.py
arrowport/config/streams.py
arrowport/core/__init__.py
arrowport/core/arrow.py
arrowport/core/db.py
arrowport/core/flight.py
arrowport/core/metrics.py
arrowport/core/storage.py
arrowport/core/tasks.py
arrowport/docs/benchmarks.md
arrowport/models/__init__.py
arrowport/models/arrow.py
arrowport/tests/conftest.py
arrowport/tests/test_api.py
arrowport/tests/test_arrow.py
arrowport/tests/test_basic.py
arrowport/tests/test_delta.py
arrowport/utils/__init__.py
arrowport-0.2.0.dist-info/licenses/LICENSE
arrowport-0.2.0.dist-info/METADATA
arrowport-0.2.0.dist-info/WHEEL
arrowport-0.2.0.dist-info/entry_points.txt
arrowport-0.2.0.dist-info/top_level.txt
arrowport-0.2.0.dist-info/RECORD
