Metadata-Version: 2.4
Name: arrowport
Version: 0.2.0
Summary: High-performance bridge from Arrow IPC streams to DuckDB
Author-email: TFMV <mcgeehan@gmail.com>
License-Expression: MIT
Classifier: Development Status :: 4 - Beta
Classifier: Intended Audience :: Developers
Classifier: Operating System :: OS Independent
Classifier: Programming Language :: Python :: 3
Classifier: Programming Language :: Python :: 3.9
Classifier: Programming Language :: Python :: 3.10
Classifier: Programming Language :: Python :: 3.11
Requires-Python: >=3.9
License-File: LICENSE
Requires-Dist: duckdb>=1.3.0
Requires-Dist: pyarrow>=20.0.0
Requires-Dist: fastapi>=0.95.0
Requires-Dist: uvicorn>=0.20.0
Requires-Dist: pydantic>=2.0.0
Requires-Dist: pydantic-settings>=2.0.0
Requires-Dist: structlog>=23.0.0
Requires-Dist: prometheus-client>=0.16.0
Requires-Dist: rich>=13.0.0
Requires-Dist: click>=8.0.0
Requires-Dist: PyYAML>=6.0.0
Requires-Dist: python-multipart>=0.0.5
Requires-Dist: zstandard>=0.20.0
Requires-Dist: lz4>=4.0.0
Requires-Dist: watchdog>=3.0.0
Dynamic: license-file
